balif/__init__.py
balif/active_learning.py
balif/bad.py
balif/iforest.py
balif/odds_datasets/__init__.py
balif/odds_datasets/annthyroid.mat
balif/odds_datasets/breastw.mat
balif/odds_datasets/cardio.mat
balif/odds_datasets/cover.mat
balif/odds_datasets/ionosphere.mat
balif/odds_datasets/letter.mat
balif/odds_datasets/mammography.mat
balif/odds_datasets/mnist.mat
balif/odds_datasets/optdigits.mat
balif/odds_datasets/pendigits.mat
balif/odds_datasets/pima.mat
balif/odds_datasets/satellite.mat
balif/odds_datasets/satimage-2.mat
balif/odds_datasets/thyroid.mat
balif/odds_datasets/vertebral.mat
balif/odds_datasets/vowels.mat
balif/odds_datasets/wbc.mat
balif/odds_datasets/wine.mat
balif-0.4.0.dist-info/METADATA
balif-0.4.0.dist-info/WHEEL
balif-0.4.0.dist-info/top_level.txt
balif-0.4.0.dist-info/RECORD
